[
  {
    "name": "Fisl 7",
    "talk": "FUMIGANT - Geração de código utilizando java e software livre",
    "date" :"2006-04-20",
    "links": {
      "agenda" : "https://web.archive.org/web/20070608003049/http://fisl.softwarelivre.org/7.0/papers/pub/",
      "description" : "https://web.archive.org/web/20070608010756/http://fisl.softwarelivre.org/7.0/papers/pub/programacao/334"
    }
  },
  {
    "name": "TDC Floripa - Java",
    "talk": "Apache Camel",
    "date": "2016-05-11",
    "links" : {
        "description" : "http://www.thedevelopersconference.com.br/tdc/2016/florianopolis/trilha-java-ee",
        "slides" : "http://slides.com/adamatti/camel"
      }
  },
  {
    "name" : "Node POA Meetup",
    "talk" : "Event Sourcing",
    "date" : "2016-07-12",
    "links" : {
      "slides" : "http://slides.com/adamatti/eventsourcing",
      "recording" : "https://www.youtube.com/watch?v=ATWEXZkYgek",
      "github" : "https://github.com/node-poa/2-meetup",
      "meetup" : "https://www.meetup.com/pt-BR/Node-js-Porto-Alegre-Meetup"
    }
  },
  {
    "name" : "DevOps Days",
    "talk" : "Don't hate your tests",
    "date" : "2016-07-09",
    "links" : {
      "slides" : "http://slides.com/adamatti/devopsday",
      "recording" : "https://www.youtube.com/watch?v=1wZGSSaDMDo",
      "page" : "http://www.devopsdays.org/events/2016-portoalegre/inicio/"
    }
  },
  {
    "name" : "RSJUG - Meetup",
    "talk" : "Grails - the search is over",
    "date" : "2016-08-03",
    "links" : {
      "slides" : "http://slides.com/adamatti/grails"
    }
  },
  {
    "name" : "TDC POA - tests",
    "talk" : "Don't hate your tests",
    "date" : "2016-10-05",
    "links" : {
      "slides" : "http://slides.com/adamatti/tdc_poa_2016_nao_dtest",
      "tweet" : "https://twitter.com/eliasnogueira/status/783682576124870656",
      "page" : "http://www.thedevelopersconference.com.br/tdc/2016/portoalegre/trilha-testes"
    }
  },
  {
    "name" : "TDC POA - javascript",
    "talk" : "Event sourcing",
    "date" : "2016-10-05",
    "links" : {
      "slides" : "http://slides.com/adamatti/eventsourcing",
      "tweet" : "https://twitter.com/alinedecampos/status/783759425106505728",
      "page" : "http://www.thedevelopersconference.com.br/tdc/2016/portoalegre/trilha-javascript"
    }
  },
  {
    "name" : "TDC POA - architecture",
    "talk" : "Event sourcing",
    "date" : "2016-10-07",
    "links" : {
      "slides" : "http://slides.com/adamatti/tdc_poa_2016_event_sourcing_arch",
      "tweet1" : "https://twitter.com/__cure/status/784461126474067969",
      "tweet2" : "https://twitter.com/toff63/status/784460801511985152",
      "page" : "http://www.thedevelopersconference.com.br/tdc/2016/portoalegre/trilha-arquitetura"
    }
  },
  {
    "name" : "Node POA Meetup",
    "talk" : "Why Node",
    "date" : "2017-03-14",
    "links" : {
      "slides" : "http://slides.com/adamatti/whynode",
      "pptx" : "https://drive.google.com/file/d/0B2LXDhHXNPKxWmlFSUR4aVMyRkE/view?usp=drivesdk",
      "github" : "https://github.com/node-poa/Meetups/blob/master/meetups/04.md",
      "meetup" : "https://www.meetup.com/pt-BR/Node-js-Porto-Alegre-Meetup"
    }
  }
]
